setup.cfg
setup.py
pythrifthiveapi/__init__.py
pythrifthiveapi.egg-info/PKG-INFO
pythrifthiveapi.egg-info/SOURCES.txt
pythrifthiveapi.egg-info/dependency_links.txt
pythrifthiveapi.egg-info/not-zip-safe
pythrifthiveapi.egg-info/requires.txt
pythrifthiveapi.egg-info/top_level.txt
pythrifthiveapi/TCLIService/TCLIService.py
pythrifthiveapi/TCLIService/__init__.py
pythrifthiveapi/TCLIService/constants.py
pythrifthiveapi/TCLIService/ttypes.py