Metadata-Version: 1.1
Name: pythrifthiveapi
Version: 0.1.1.0
Summary: Thrift Schema and python client for the Hive Thrift API.
Home-page: https://git.musta.ch/bkyryliuk/pythrifthiveapi
Author: Bogdan Kyryliuk
Author-email: b.kyryliuk@gmail.com
License: UNKNOWN
Download-URL: https://github.com/bkyryliuk/pythrifthiveapi/tarball/0.1.1.0
Platform: UNKNOWN
Classifier: Programming Language :: Python :: 2.7
Classifier: Programming Language :: Python :: 3.4
Classifier: Programming Language :: Python :: 3.5
